[
    {
        "id": "691",
        "rare": 3
    },
    {
        "id": "674",
        "rare": 3
    },
    {
        "id": "585",
        "rare": 3
    },
    {
        "id": "582",
        "rare": 3
    },
    {
        "id": "581",
        "rare": 3
    },
    {
        "id": "580",
        "rare": 3
    },
    {
        "id": "545",
        "rare": 3
    },
    {
        "id": "420",
        "rare": 3
    },
    {
        "id": "419",
        "rare": 3
    },
    {
        "id": "418",
        "rare": 3
    },
    {
        "id": "402",
        "rare": 3
    },
    {
        "id": "401",
        "rare": 4
    },
    {
        "id": "400",
        "rare": 5
    },
    {
        "id": "333",
        "rare": 3
    },
    {
        "id": "332",
        "rare": 3
    },
    {
        "id": "331",
        "rare": 3
    },
    {
        "id": "265",
        "rare": 3
    },
    {
        "id": "264",
        "rare": 4
    },
    {
        "id": "263",
        "rare": 5
    },
    {
        "id": "247",
        "rare": 3
    },
    {
        "id": "246",
        "rare": 3
    },
    {
        "id": "245",
        "rare": 3
    },
    {
        "id": "244",
        "rare": 3
    },
    {
        "id": "243",
        "rare": 3
    },
    {
        "id": "188",
        "rare": 5
    },
    {
        "id": "186",
        "rare": 4
    },
    {
        "id": "185",
        "rare": 5
    },
    {
        "id": "184",
        "rare": 4
    },
    {
        "id": "183",
        "rare": 4
    },
    {
        "id": "182",
        "rare": 4
    },
    {
        "id": "176",
        "rare": 4
    },
    {
        "id": "175",
        "rare": 5
    },
    {
        "id": "98",
        "rare": 4
    },
    {
        "id": "97",
        "rare": 5
    },
    {
        "id": "91",
        "rare": 3
    },
    {
        "id": "89",
        "rare": 3
    },
    {
        "id": "75",
        "rare": 5
    },
    {
        "id": "74",
        "rare": 4
    },
    {
        "id": "73",
        "rare": 4
    },
    {
        "id": "67",
        "rare": 5
    },
    {
        "id": "66",
        "rare": 4
    },
    {
        "id": "58",
        "rare": 5
    },
    {
        "id": "57",
        "rare": 5
    },
    {
        "id": "56",
        "rare": 4
    },
    {
        "id": "48",
        "rare": 5
    },
    {
        "id": "47",
        "rare": 4
    },
    {
        "id": "40",
        "rare": 5
    },
    {
        "id": "39",
        "rare": 4
    },
    {
        "id": "38",
        "rare": 4
    },
    {
        "id": "35",
        "rare": 5
    },
    {
        "id": "34",
        "rare": 5
    },
    {
        "id": "33",
        "rare": 5
    },
    {
        "id": "32",
        "rare": 5
    },
    {
        "id": "31",
        "rare": 5
    },
    {
        "id": "30",
        "rare": 4
    },
    {
        "id": "29",
        "rare": 4
    },
    {
        "id": "28",
        "rare": 4
    },
    {
        "id": "27",
        "rare": 4
    },
    {
        "id": "26",
        "rare": 4
    },
    {
        "id": "25",
        "rare": 4
    },
    {
        "id": "24",
        "rare": 4
    },
    {
        "id": "23",
        "rare": 4
    },
    {
        "id": "22",
        "rare": 4
    },
    {
        "id": "21",
        "rare": 4
    }
]